bdrc_transfer-0.1.21.data/scripts/audit-gb
bdrc_transfer-0.1.21.data/scripts/gb-audit-tool.config
bdrc_transfer-0.1.21.data/scripts/hiddenexclude.lst
gb_config/__init__.py
gb_config/gb_config.py
gb_config/grin.config
gb_config/__pycache__/gb_config.cpython-311.pyc
gb_lib/GbLib.py
gb_lib/__init__.py
gb_lib/Tests/GB_config_test.py
gb_lib/Tests/__init__.py
gb_lib/Tests/test_parse.py
gb_lib/__pycache__/__init__.cpython-311.pyc
gb_ocr/GRINConfig.py
gb_ocr/__init__.py
gb_ocr/create_metadata.py
gb_ocr/dimensions_to_gbinfo.py
gb_ocr/distribute.py
gb_ocr/distribute_ocr.py
gb_ocr/distribute_ocr_no_class.py
gb_ocr/download.py
gb_ocr/ftp_transfer.py
gb_ocr/relocate_downloads.py
gb_ocr/request_conversion.py
gb_ocr/unpack.py
gb_ocr/unpack_no_class.py
gb_ocr/upload_archive.py
gb_ocr/upload_metadata.py
gb_ocr/__pycache__/__init__.cpython-311.pyc
gb_ocr/grin_lib/GRINOps.py
gb_ocr/grin_lib/__init__.py
gb_ocr/grin_lib/grin_oauth3.py
log_ocr/AORunLog.py
log_ocr/DrsContextBase.py
log_ocr/GbOcrTrack.py
log_ocr/__init__.py
log_ocr/__pycache__/__init__.cpython-311.pyc
log_ocr/models/__init__.py
log_ocr/models/drs.py
test/__init__.py
test/testGbOcrDownloads.py
test/test_GRINOps.py
bdrc_transfer-0.1.21.dist-info/METADATA
bdrc_transfer-0.1.21.dist-info/WHEEL
bdrc_transfer-0.1.21.dist-info/entry_points.txt
bdrc_transfer-0.1.21.dist-info/top_level.txt
bdrc_transfer-0.1.21.dist-info/RECORD
