Metadata-Version: 2.1
Name: bdrc-transfer
Version: 0.1.21
Summary: Transfer library
Home-page: UNKNOWN
Author: jimk
Author-email: jimk@tbrc.org
License: UNKNOWN
Platform: UNKNOWN
Classifier: Programming Language :: Python :: 3
Classifier: License :: OSI Approved :: MIT License
Classifier: Operating System :: OS Independent
Classifier: Development Status :: 3 - Alpha
Requires-Python: >=3.8
Requires-Dist: paramiko
Requires-Dist: urllib3
Requires-Dist: bdrc-util
Requires-Dist: sqlalchemy
Requires-Dist: boto3
Requires-Dist: botocore
Requires-Dist: bdrc-db-lib
Requires-Dist: mysqlclient
Requires-Dist: oauth2client
